errfriendly/__init__.py
errfriendly/ai_explainer.py
errfriendly/audit.py
errfriendly/context_collector.py
errfriendly/exception_graph.py
errfriendly/handler.py
errfriendly/messages.py
errfriendly/models.py
errfriendly/py.typed
errfriendly/warning_handler.py
errfriendly-3.4.2.dist-info/licenses/LICENSE
errfriendly-3.4.2.dist-info/METADATA
errfriendly-3.4.2.dist-info/WHEEL
errfriendly-3.4.2.dist-info/top_level.txt
errfriendly-3.4.2.dist-info/RECORD
