Metadata-Version: 2.4
Name: errfriendly
Version: 3.4.2
Summary: Friendly explanations for Python errors
Author-email: "https://github.com/infinawaz" <shahnawazdgp07@gmail.com>
License: MIT
Project-URL: Homepage, https://github.com/infinawaz/errfriendly
Project-URL: Documentation, https://github.com/infinawaz/errfriendly#readme
Project-URL: Repository, https://github.com/infinawaz/errfriendly
Project-URL: Issues, https://github.com/infinawaz/errfriendly/issues
Keywords: exceptions,debugging,developer-tools,error-messages,traceback,ai,llm,ollama,openai
Classifier: Development Status :: 4 - Beta
Classifier: Intended Audience :: Developers
Classifier: License :: OSI Approved :: MIT License
Classifier: Operating System :: OS Independent
Classifier: Programming Language :: Python :: 3
Classifier: Programming Language :: Python :: 3.8
Classifier: Programming Language :: Python :: 3.9
Classifier: Programming Language :: Python :: 3.10
Classifier: Programming Language :: Python :: 3.11
Classifier: Programming Language :: Python :: 3.12
Classifier: Topic :: Software Development :: Debuggers
Classifier: Topic :: Software Development :: Libraries :: Python Modules
Classifier: Typing :: Typed
Requires-Python: >=3.8
License-File: LICENSE
Provides-Extra: dev
Requires-Dist: pytest>=7.0.0; extra == "dev"
Requires-Dist: pytest-cov>=4.0.0; extra == "dev"
Requires-Dist: build>=1.0.0; extra == "dev"
Provides-Extra: ai-local
Requires-Dist: httpx>=0.24.0; extra == "ai-local"
Provides-Extra: ai-deepseek
Requires-Dist: openai>=1.0.0; extra == "ai-deepseek"
Provides-Extra: ai-openai
Requires-Dist: openai>=1.0.0; extra == "ai-openai"
Provides-Extra: ai-anthropic
Requires-Dist: anthropic>=0.18.0; extra == "ai-anthropic"
Provides-Extra: ai-gemini
Requires-Dist: google-generativeai>=0.4.0; extra == "ai-gemini"
Provides-Extra: ai-all
Requires-Dist: httpx>=0.24.0; extra == "ai-all"
Requires-Dist: openai>=1.0.0; extra == "ai-all"
Requires-Dist: anthropic>=0.18.0; extra == "ai-all"
Requires-Dist: google-generativeai>=0.4.0; extra == "ai-all"
Dynamic: license-file
